ownotp/__init__.py
ownotp/otp.py
ownotp-0.1.2.dist-info/LICENSE
ownotp-0.1.2.dist-info/METADATA
ownotp-0.1.2.dist-info/WHEEL
ownotp-0.1.2.dist-info/top_level.txt
ownotp-0.1.2.dist-info/RECORD
