Metadata-Version: 2.1
Name: ownotp
Version: 0.1.2
Summary: Generate a time-based OTP using SHA-256 hashing algorithm
Home-page: https://github.com/karthiksenniyappan/ownotp
Author: karthiksenniyappan
Author-email: karthiksenniyappan76@gmail.com
Classifier: Programming Language :: Python :: 3
Classifier: License :: OSI Approved :: MIT License
Classifier: Operating System :: OS Independent
Requires-Python: >=3.6
License-File: LICENSE
